SBG_TIR_granules/L1CTRAD.py
SBG_TIR_granules/L2TLSTE.py
SBG_TIR_granules/L2TSTARS.py
SBG_TIR_granules/L4TESI.py
SBG_TIR_granules/L4TJET.py
SBG_TIR_granules/L4TWUE.py
SBG_TIR_granules/SBG_TIR_granules.py
SBG_TIR_granules/__init__.py
SBG_TIR_granules/colors.py
SBG_TIR_granules/granule.py
SBG_TIR_granules/open_granule.py
SBG_TIR_granules/tiled_granule.py
SBG_TIR_granules/version.txt
SBG_TIR_granules/write_XML_metadata.py
SBG_TIR_granules/timer/__init__.py
SBG_TIR_granules/timer/timer.py
sbg_tir_granules-0.1.2.dist-info/LICENSE
sbg_tir_granules-0.1.2.dist-info/METADATA
sbg_tir_granules-0.1.2.dist-info/WHEEL
sbg_tir_granules-0.1.2.dist-info/top_level.txt
sbg_tir_granules-0.1.2.dist-info/RECORD
